cpalette
