Metadata-Version: 2.1
Name: cpalette
Version: 1.0.2
Summary: Color palette is a python library for working with 
Home-page: https://github.com/chebupelka8/color_palette
Author: chebupelka8
Author-email: stpzamyatin@gmail.com
Classifier: Programming Language :: Python :: 3.11
Classifier: License :: OSI Approved :: MIT License
Classifier: Operating System :: OS Independent
Requires-Python: >=3.7
License-File: LICENSE
Requires-Dist: pillow
